colorpalette/__init__.py
colorpalette/color.py
colorpalette/color_scheme.py
colorpalette-0.1.0.dist-info/METADATA
colorpalette-0.1.0.dist-info/WHEEL
colorpalette-0.1.0.dist-info/top_level.txt
colorpalette-0.1.0.dist-info/RECORD
