Metadata-Version: 2.1
Name: colorpalette
Version: 0.1.0
Summary: Objects for coloring strings
Home-page: https://github.com/yoelcortes/colorpalette
Author: Yoel Cortes-Pena
Author-email: yoelcortes@gmail.com
License: MIT
Download-URL: https://github.com/yoelcortes/colorpalette.git
Platform: Windows
Requires-Dist: ansicolors
Requires-Dist: colorama
